<bill session="109" type="h" number="6027" updated="2013-07-19T19:57:39-04:00">
  <state datetime="2006-08-02">REFERRED</state>
  <status>
    <introduced datetime="2006-08-02"/>
  </status>
  <introduced datetime="2006-08-02"/>
  <titles>
    <title as="introduced" type="short">Volunteer Emergency Services Recruitment and Retention Act of 2006</title>
    <title as="introduced" type="official">To amend the Internal Revenue Code of 1986 to provide recruitment and retention incentives for volunteer emergency service workers.</title>
  </titles>
  <sponsor id="400219"/>
  <cosponsors>
    <cosponsor id="400153" joined="2006-09-06"/>
    <cosponsor id="400306" joined="2006-09-28"/>
  </cosponsors>
  <actions>
    <action state="REFERRED" datetime="2006-08-02">
      <text>Referred to the Committee on Ways and Means, and in addition to the Committee on Education and the Workforce, for a period to be subsequently determined by the Speaker, in each case for consideration of such provisions as fall within the jurisdiction of the committee concerned.</text>
    </action>
    <action datetime="2006-08-02">
      <text>Referred to House Ways and Means</text>
    </action>
    <action datetime="2006-08-02">
      <text>Referred to House Education and the Workforce</text>
    </action>
    <action datetime="2006-09-28">
      <text>Referred to the Subcommittee on Employer-Employee Relations.</text>
      <committee name="House Education and the Workforce"/>
    </action>
  </actions>
  <committees>
    <committee code="HSWM" name="House Ways and Means" activity="Referral, In Committee"/>
    <committee code="HSED" name="House Education and the Workforce" activity="Referral, In Committee"/>
    <committee activity="Referral" code="HSED02" subcommittee="Employer-Employee Relations" name="House Education and the Workforce"/>
  </committees>
  <relatedbills/>
  <subjects>
    <term name="Taxation"/>
    <term name="Accounting"/>
    <term name="Administrative procedure"/>
    <term name="Cost of living adjustments"/>
    <term name="Department of Labor"/>
    <term name="Economics and public finance"/>
    <term name="Emergency management"/>
    <term name="Finance and financial sector"/>
    <term name="Fire fighters"/>
    <term name="Government operations and politics"/>
    <term name="Health"/>
    <term name="Income tax"/>
    <term name="Indexing (Economic policy)"/>
    <term name="Labor and employment"/>
    <term name="Law"/>
    <term name="Paramedical personnel"/>
    <term name="Social welfare"/>
    <term name="Tax-deferred compensation plans"/>
    <term name="Volunteer workers"/>
  </subjects>
  <amendments/>
  <summary>8/2/2006--Introduced.
Volunteer Emergency Services Recruitment and Retention Act of 2006 - Amends the Internal Revenue Code to allow sponsors of certain deferred compensation plans to elect to include length of service award plans for bona fide volunteers providing fire fighting and prevention services, emergency medical services, and emergency rescue services. Directs the Secretary of Labor to issue regulations exempting a length of service award program from treatment as an employee pension benefit plan under the Employee Retirement Income Security Act of 1974 (ERISA).</summary>
</bill>
