<bill session="111" type="s" number="3118" updated="2013-07-20T00:53:47-04:00">
  <state datetime="2010-03-16">REFERRED</state>
  <status>
    <introduced datetime="2010-03-16"/>
  </status>
  <introduced datetime="2010-03-16"/>
  <titles>
    <title as="introduced" type="short">Veterans Pensions Protection Act</title>
    <title as="introduced" type="official">A bill to amend title 38, United States Code, to provide that monetary benefits paid to veterans by States and municipalities shall be excluded from consideration as income for purposes of pension benefits paid by the Secretary of Veterans Affairs.</title>
  </titles>
  <sponsor id="300060"/>
  <cosponsors/>
  <actions>
    <action state="REFERRED" datetime="2010-03-16">
      <text>Read twice and referred to the Committee on Veterans' Affairs.</text>
    </action>
  </actions>
  <committees>
    <committee code="SSVA" name="Senate Veterans' Affairs" activity="Referral, In Committee"/>
  </committees>
  <relatedbills>
    <bill relation="identical" session="111" type="h" number="3485"/>
  </relatedbills>
  <subjects>
    <term name="Armed forces and national security"/>
    <term name="Veterans' pensions and compensation"/>
  </subjects>
  <amendments/>
  <summary>3/16/2010--Introduced.
Veterans Pensions Protection Act - Excludes monetary veterans' benefits paid to a veteran from a state or municipality from consideration as income for purposes of pension benefits paid by the Secretary of Veterans Affairs (VA).</summary>
</bill>
