<bill session="111" type="s" number="1821" updated="2013-07-20T00:40:05-04:00">
  <state datetime="2009-10-21">REFERRED</state>
  <status>
    <introduced datetime="2009-10-21"/>
  </status>
  <introduced datetime="2009-10-21"/>
  <titles>
    <title as="introduced" type="short">Elder Abuse Victims Act of 2009</title>
    <title as="introduced" type="official">A bill to protect seniors in the United States from elder abuse by establishing specialized elder abuse prosecution and research programs and activities to aid victims of elder abuse, to provide training to prosecutors and other law enforcement related to elder abuse prevention and protection, to establish programs that provide for emergency crisis response teams to combat elder abuse, and for other purposes.</title>
  </titles>
  <sponsor id="300061"/>
  <cosponsors>
    <cosponsor id="400050" joined="2010-11-15"/>
    <cosponsor id="300065" joined="2009-10-21"/>
    <cosponsor id="412380" joined="2009-10-21"/>
    <cosponsor id="300073" joined="2009-10-21"/>
    <cosponsor id="300078" joined="2009-10-27"/>
  </cosponsors>
  <actions>
    <action state="REFERRED" datetime="2009-10-21">
      <text>Read twice and referred to the Committee on the Judiciary.</text>
    </action>
  </actions>
  <committees>
    <committee code="SSJU" name="Senate Judiciary" activity="Referral, In Committee"/>
  </committees>
  <relatedbills>
    <bill relation="unknown" session="111" type="h" number="448"/>
  </relatedbills>
  <subjects>
    <term name="Crime and law enforcement"/>
    <term name="Aging"/>
    <term name="Crime victims"/>
    <term name="Criminal investigation, prosecution, interrogation"/>
    <term name="Criminal justice information and records"/>
    <term name="Domestic violence and child abuse"/>
    <term name="Employment and training programs"/>
    <term name="Fraud offenses and financial crimes"/>
    <term name="Government information and archives"/>
    <term name="Government studies and investigations"/>
    <term name="Homelessness and emergency shelter"/>
    <term name="Housing for the elderly and disabled"/>
    <term name="Judicial procedure and administration"/>
    <term name="Law enforcement administration and funding"/>
    <term name="Law enforcement officers"/>
    <term name="Lawyers and legal services"/>
    <term name="Medicaid"/>
    <term name="Mental health"/>
    <term name="Poverty and welfare assistance"/>
    <term name="Social security and elderly assistance"/>
    <term name="State and local courts"/>
    <term name="State and local government operations"/>
  </subjects>
  <amendments/>
  <summary>10/21/2009--Introduced.
Elder Abuse Victims Act of 2009 - Directs the Attorney General to: (1) study state laws and practices relating to elder abuse, neglect, and exploitation and report to Congress on such study; (2) develop a long-term plan for elder justice programs and activities; (3) award grants to support and train state and local prosecutors, courts, and law enforcement personnel handling elder justice-related matters; and (4) establish the Elder Serve Victim grant program to facilitate and coordinate programs to provide emergency services to victims of elder abuse.</summary>
</bill>
