<bill session="109" type="s" number="1452" updated="2013-07-19T20:26:14-04:00">
  <state datetime="2005-07-21">REFERRED</state>
  <status>
    <introduced datetime="2005-07-21"/>
  </status>
  <introduced datetime="2005-07-21"/>
  <titles>
    <title as="introduced" type="official">A bill to suspend temporarily the duty on Desmodur E 14.</title>
  </titles>
  <sponsor id="300085"/>
  <cosponsors/>
  <actions>
    <action state="REFERRED" datetime="2005-07-21">
      <text>Read twice and referred to the Committee on Finance.</text>
    </action>
  </actions>
  <committees>
    <committee code="SSFI" name="Senate Finance" activity="Referral, In Committee"/>
  </committees>
  <relatedbills>
    <bill relation="identical" session="109" type="h" number="2270"/>
  </relatedbills>
  <subjects>
    <term name="Foreign trade and international finance"/>
    <term name="Commerce"/>
    <term name="Polymers"/>
    <term name="Tariff"/>
  </subjects>
  <amendments/>
  <summary>7/21/2005--Introduced.
Amends the Harmonized Tariff Schedule of the United States to suspend, through December 31, 2008, the duty on a specific linear aromatic polyurethane prepolymer based on toluene diisocyanate (Desmodur E 14).</summary>
</bill>
