<bill session="109" type="h" number="5056" updated="2013-07-19T19:48:57-04:00">
  <state datetime="2006-03-30">REFERRED</state>
  <status>
    <introduced datetime="2006-03-30"/>
  </status>
  <introduced datetime="2006-03-30"/>
  <titles>
    <title as="introduced" type="official">To amend the Internal Revenue Code of 1986 to encourage charitable contributions of real property for conservation purposes.</title>
  </titles>
  <sponsor id="400646"/>
  <cosponsors>
    <cosponsor id="400027" joined="2006-05-17"/>
    <cosponsor id="400032" joined="2006-06-06"/>
    <cosponsor id="400033" joined="2006-03-30"/>
    <cosponsor id="400051" joined="2006-05-17"/>
    <cosponsor id="400077" joined="2006-04-27"/>
    <cosponsor id="400633" joined="2006-05-17"/>
    <cosponsor id="400108" joined="2006-06-29"/>
    <cosponsor id="400123" joined="2006-06-06"/>
    <cosponsor id="400147" joined="2006-03-30"/>
    <cosponsor id="400173" joined="2006-07-26"/>
    <cosponsor id="400213" joined="2006-05-17"/>
    <cosponsor id="400222" joined="2006-04-25"/>
    <cosponsor id="400654" joined="2006-05-17"/>
    <cosponsor id="400260" joined="2006-09-07"/>
    <cosponsor id="400276" joined="2006-05-17"/>
    <cosponsor id="400637" joined="2006-07-28"/>
    <cosponsor id="400375" joined="2006-03-30"/>
  </cosponsors>
  <actions>
    <action state="REFERRED" datetime="2006-03-30">
      <text>Referred to the House Committee on Ways and Means.</text>
    </action>
  </actions>
  <committees>
    <committee code="HSWM" name="House Ways and Means" activity="Referral, In Committee"/>
  </committees>
  <relatedbills/>
  <subjects>
    <term name="Taxation"/>
    <term name="Agricultural conservation"/>
    <term name="Agriculture and food"/>
    <term name="Capital gains tax"/>
    <term name="Charitable contributions"/>
    <term name="Commerce"/>
    <term name="Corporation taxes"/>
    <term name="Environmental protection"/>
    <term name="Farmers"/>
    <term name="Income tax"/>
    <term name="Nature conservation"/>
    <term name="Public lands and natural resources"/>
    <term name="Real property"/>
    <term name="Tax deductions"/>
  </subjects>
  <amendments/>
  <summary>3/30/2006--Introduced.
Amends the Internal Revenue Code to allow: (1) taxpayers making charitable contributions of real property for conservation purposes (qualified conservation contributions) to deduct up to 50% (currently, 30%) of their income for such contributions (100% for certain farmers or ranchers); and (2) a 15-year carryover of excess tax deduction amounts for such contributions.</summary>
</bill>
