<bill session="111" type="h" number="4264" updated="2013-07-19T23:50:49-04:00">
  <state datetime="2009-12-10">REFERRED</state>
  <status>
    <introduced datetime="2009-12-10"/>
  </status>
  <introduced datetime="2009-12-10"/>
  <titles>
    <title as="introduced" type="short">Equality for Women Farmers Act</title>
    <title as="introduced" type="official">To provide for resolution of certain discrimination claims against the Department of Agriculture, and for other purposes.</title>
  </titles>
  <sponsor id="400103"/>
  <cosponsors>
    <cosponsor id="400013" joined="2010-01-19"/>
    <cosponsor id="400124" joined="2009-12-10"/>
    <cosponsor id="400129" joined="2010-04-21"/>
    <cosponsor id="400133" joined="2010-04-21"/>
    <cosponsor id="400185" joined="2010-05-27"/>
    <cosponsor id="400227" joined="2010-05-24"/>
    <cosponsor id="412253" joined="2010-05-24"/>
    <cosponsor id="400387" joined="2009-12-16"/>
  </cosponsors>
  <actions>
    <action state="REFERRED" datetime="2009-12-10">
      <text>Referred to the Committee on the Judiciary, and in addition to the Committees on Agriculture, and Ways and Means, for a period to be subsequently determined by the Speaker, in each case for consideration of such provisions as fall within the jurisdiction of the committee concerned.</text>
    </action>
    <action datetime="2009-12-10">
      <text>Referred to House Judiciary</text>
    </action>
    <action datetime="2009-12-10">
      <text>Referred to House Agriculture</text>
    </action>
    <action datetime="2009-12-10">
      <text>Referred to House Ways and Means</text>
    </action>
    <action datetime="2010-03-29">
      <text>Referred to the Subcommittee on Conservation, Credit, Energy, and Research.</text>
      <committee name="House Agriculture"/>
    </action>
  </actions>
  <committees>
    <committee code="HSJU" name="House Judiciary" activity="Referral, In Committee"/>
    <committee code="HSAG" name="House Agriculture" activity="Referral, In Committee"/>
    <committee activity="Referral" code="HSAG15" subcommittee="Conservation, Credit, Energy, and Research" name="House Agriculture"/>
    <committee code="HSWM" name="House Ways and Means" activity="Referral, In Committee"/>
  </committees>
  <relatedbills/>
  <subjects>
    <term name="Civil rights and liberties, minority issues"/>
    <term name="Administrative remedies"/>
    <term name="Agricultural prices, subsidies, credit"/>
    <term name="Alternative dispute resolution, mediation, arbitration"/>
    <term name="Department of Agriculture"/>
    <term name="Disaster relief and insurance"/>
    <term name="Government information and archives"/>
    <term name="Government lending and loan guarantees"/>
    <term name="Government liability"/>
    <term name="Government studies and investigations"/>
    <term name="Legal fees and court costs"/>
    <term name="Minority and disadvantaged businesses"/>
    <term name="Sex, gender, sexual orientation discrimination"/>
    <term name="Women in business"/>
  </subjects>
  <amendments/>
  <summary>12/10/2009--Introduced.
Equality for Women Farmers Act - Directs the Secretary of Agriculture to attempt to notify potential claimants of a three-year opportunity to submit a claim for gender discrimination damages against the Department of Agriculture for failing to provide or review applications for farm loans, farm loan servicing, or disaster loans during the period January 1, 1981, through the date of enactment of this Act. Directs the Federal Mediation and Conciliation Service to appoint a Special Master to adjudicate such claims. Prohibits the Department from initiating foreclosure on collateral or secured property of an eligible claimant during such three-year period. Sets forth audit and reporting provisions.</summary>
</bill>
