<bill session="110" type="sr" number="660" updated="2013-07-19T22:18:41-04:00">
  <state datetime="2008-09-27">PASSED:SIMPLERES</state>
  <status>
    <unknown datetime="2008-09-27"/>
  </status>
  <introduced datetime="2008-09-15"/>
  <titles>
    <title as="introduced" type="official">A resolution condemning ongoing sales of arms to belligerents in Sudan, including the Government of Sudan, and calling for both a cessation of such sales and an expansion of the United Nations embargo on arms sales to Sudan.</title>
  </titles>
  <sponsor id="300078"/>
  <cosponsors>
    <cosponsor id="300009" joined="2008-09-18"/>
    <cosponsor id="300011" joined="2008-09-15"/>
    <cosponsor id="300013" joined="2008-09-15"/>
    <cosponsor id="400054" joined="2008-09-23"/>
    <cosponsor id="400064" joined="2008-09-15"/>
    <cosponsor id="412246" joined="2008-09-15"/>
    <cosponsor id="300021" joined="2008-09-22"/>
    <cosponsor id="300022" joined="2008-09-15"/>
    <cosponsor id="300024" joined="2008-09-15"/>
    <cosponsor id="300025" joined="2008-09-26"/>
    <cosponsor id="300035" joined="2008-09-15"/>
    <cosponsor id="300038" joined="2008-09-15"/>
    <cosponsor id="300040" joined="2008-09-22"/>
    <cosponsor id="300042" joined="2008-09-15"/>
    <cosponsor id="300051" joined="2008-09-17"/>
    <cosponsor id="300052" joined="2008-09-15"/>
    <cosponsor id="300055" joined="2008-09-15"/>
    <cosponsor id="400194" joined="2008-09-15"/>
    <cosponsor id="300060" joined="2008-09-15"/>
    <cosponsor id="300063" joined="2008-09-22"/>
    <cosponsor id="300067" joined="2008-09-15"/>
    <cosponsor id="400621" joined="2008-09-15"/>
    <cosponsor id="400272" joined="2008-09-15"/>
    <cosponsor id="300090" joined="2008-09-22"/>
    <cosponsor id="300091" joined="2008-09-15"/>
    <cosponsor id="300092" joined="2008-09-23"/>
    <cosponsor id="300095" joined="2008-09-22"/>
    <cosponsor id="300098" joined="2008-09-22"/>
    <cosponsor id="412247" joined="2008-09-17"/>
  </cosponsors>
  <actions>
    <action datetime="2008-09-15">
      <text>Sponsor introductory remarks on measure.</text>
      <reference ref="CR S8532-8533"/>
    </action>
    <action state="REFERRED" datetime="2008-09-15">
      <text>Referred to the Committee on Foreign Relations.</text>
      <reference ref="CR S8531-8532" label="text of measure as introduced"/>
    </action>
    <action datetime="2008-09-27">
      <text>Senate Committee on Foreign Relations discharged by Unanimous Consent.</text>
    </action>
    <action datetime="2008-09-27">
      <text>Measure laid before Senate by unanimous consent.</text>
      <reference ref="CR S10019" label="consideration"/>
    </action>
    <vote state="PASSED:SIMPLERES" datetime="2008-09-27" how="by Unanimous Consent" result="pass" type="vote" where="s">
      <text>Resolution agreed to in Senate with an amendment and with a preamble by Unanimous Consent.</text>
    </vote>
  </actions>
  <committees>
    <committee code="SSFR" name="Senate Foreign Relations" activity="Referral, Discharged"/>
  </committees>
  <relatedbills>
    <bill relation="identical" session="110" type="hr" number="1462"/>
  </relatedbills>
  <subjects>
    <term name="International affairs"/>
    <term name="Africa (Sub-Saharan)"/>
    <term name="Armed forces and national security"/>
    <term name="Arms sales"/>
    <term name="China"/>
    <term name="East Asia"/>
    <term name="Embargo"/>
    <term name="Foreign trade and international finance"/>
    <term name="Government operations and politics"/>
    <term name="Insurgency"/>
    <term name="International military forces"/>
    <term name="Peace negotiations"/>
    <term name="Peacekeeping forces"/>
    <term name="Regionalism (International organization)"/>
    <term name="Russia"/>
    <term name="Sanctions (International law)"/>
    <term name="Sudan"/>
    <term name="United Nations"/>
  </subjects>
  <amendments>
    <amendment number="s5675"/>
  </amendments>
  <summary>9/27/2008--Passed Senate amended.
Expresses the sense of the Senate that: (1) the United States should seek a peaceful resolution to the conflict in Darfur, Sudan, and should continue to pursue a political solution to the deployment of the United Nations-African Union Mission peacekeeping forces in Darfur; (2) the United States supports U.N. Security Council Resolutions 1556 and 1591 imposing an arms embargo on all belligerents in Darfur; (3) in light of the transferred arms in Darfur from China and Russia and the government of Sudan's insistence that it will not abide by the embargo, all U.N. member states should cease all arms sales to the government of Sudan; and (4) the U.S. Permanent Representative to the United Nations should seek an expansion of the arms embargo imposed by Resolutions 1556 and 1591.</summary>
</bill>
